ado_task_manager/__init__.py
ado_task_manager/cli.py
ado_task_manager/client.py
ado_task_manager/config.py
ado_task_manager/errors.py
ado_task_manager/models.py
ado_task_manager/server.py
ado_task_manager/service.py
ado_task_manager-0.1.5.dist-info/METADATA
ado_task_manager-0.1.5.dist-info/WHEEL
ado_task_manager-0.1.5.dist-info/entry_points.txt
ado_task_manager-0.1.5.dist-info/top_level.txt
ado_task_manager-0.1.5.dist-info/RECORD
