Metadata-Version: 2.4
Name: ado-task-manager
Version: 0.1.5
Summary: Azure DevOps Task Manager MCP
Author: Om Surushe
Requires-Python: >=3.10
Requires-Dist: requests>=2.31
Requires-Dist: typer>=0.9
Requires-Dist: pydantic>=2.0
Requires-Dist: fastapi>=0.110
Requires-Dist: uvicorn>=0.27
Requires-Dist: mcp>=0.3.0
Requires-Dist: python-dotenv>=1.0
